[
    {
        "jmhVersion" : "1.37",
        "benchmark" : "me.ahoo.wow.benchmark.component.AggregateHandleComponentBenchmark.processCommandAggregate",
        "mode" : "thrpt",
        "threads" : 16,
        "forks" : 1,
        "jvm" : "/Library/Java/JavaVirtualMachines/zulu-17.jdk/Contents/Home/bin/java",
        "jvmArgs" : [
            "-Xms2g",
            "-Xmx2g",
            "-XX:+UseG1GC"
        ],
        "jdkVersion" : "17.0.7",
        "vmName" : "OpenJDK 64-Bit Server VM",
        "vmVersion" : "17.0.7+7-LTS",
        "warmupIterations" : 2,
        "warmupTime" : "2 s",
        "warmupBatchSize" : 1,
        "measurementIterations" : 5,
        "measurementTime" : "2 s",
        "measurementBatchSize" : 1,
        "primaryMetric" : {
            "score" : 991341.2519042889,
            "scoreError" : 13174.783414208709,
            "scoreConfidence" : [
                978166.4684900802,
                1004516.0353184976
            ],
            "scorePercentiles" : {
                "0.0" : 987427.6328349503,
                "50.0" : 990573.6775236516,
                "90.0" : 996768.1984009456,
                "95.0" : 996768.1984009456,
                "99.0" : 996768.1984009456,
                "99.9" : 996768.1984009456,
                "99.99" : 996768.1984009456,
                "99.999" : 996768.1984009456,
                "99.9999" : 996768.1984009456,
                "100.0" : 996768.1984009456
            },
            "scoreUnit" : "ops/s",
            "rawData" : [
                [
                    991739.6916744672,
                    987427.6328349503,
                    996768.1984009456,
                    990573.6775236516,
                    990197.0590874297
                ]
            ]
        },
        "secondaryMetrics" : {
            "gc.alloc.rate" : {
                "score" : 4839.078304914208,
                "scoreError" : 64.05901025406747,
                "scoreConfidence" : [
                    4775.019294660141,
                    4903.137315168276
                ],
                "scorePercentiles" : {
                    "0.0" : 4819.852437231745,
                    "50.0" : 4835.4682040914,
                    "90.0" : 4865.379859299468,
                    "95.0" : 4865.379859299468,
                    "99.0" : 4865.379859299468,
                    "99.9" : 4865.379859299468,
                    "99.99" : 4865.379859299468,
                    "99.999" : 4865.379859299468,
                    "99.9999" : 4865.379859299468,
                    "100.0" : 4865.379859299468
                },
                "scoreUnit" : "MB/sec",
                "rawData" : [
                    [
                        4840.990496153693,
                        4819.852437231745,
                        4865.379859299468,
                        4835.4682040914,
                        4833.7005277947355
                    ]
                ]
            },
            "gc.alloc.rate.norm" : {
                "score" : 5120.004459985022,
                "scoreError" : 8.335429619737217E-5,
                "scoreConfidence" : [
                    5120.004376630725,
                    5120.004543339318
                ],
                "scorePercentiles" : {
                    "0.0" : 5120.004439128204,
                    "50.0" : 5120.004447782175,
                    "90.0" : 5120.004486397951,
                    "95.0" : 5120.004486397951,
                    "99.0" : 5120.004486397951,
                    "99.9" : 5120.004486397951,
                    "99.99" : 5120.004486397951,
                    "99.999" : 5120.004486397951,
                    "99.9999" : 5120.004486397951,
                    "100.0" : 5120.004486397951
                },
                "scoreUnit" : "B/op",
                "rawData" : [
                    [
                        5120.004446416158,
                        5120.004486397951,
                        5120.004447782175,
                        5120.004439128204,
                        5120.004480200623
                    ]
                ]
            },
            "gc.count" : {
                "score" : 40.0,
                "scoreError" : "NaN",
                "scoreConfidence" : [
                    40.0,
                    40.0
                ],
                "scorePercentiles" : {
                    "0.0" : 8.0,
                    "50.0" : 8.0,
                    "90.0" : 8.0,
                    "95.0" : 8.0,
                    "99.0" : 8.0,
                    "99.9" : 8.0,
                    "99.99" : 8.0,
                    "99.999" : 8.0,
                    "99.9999" : 8.0,
                    "100.0" : 8.0
                },
                "scoreUnit" : "counts",
                "rawData" : [
                    [
                        8.0,
                        8.0,
                        8.0,
                        8.0,
                        8.0
                    ]
                ]
            },
            "gc.time" : {
                "score" : 37.0,
                "scoreError" : "NaN",
                "scoreConfidence" : [
                    37.0,
                    37.0
                ],
                "scorePercentiles" : {
                    "0.0" : 7.0,
                    "50.0" : 7.0,
                    "90.0" : 9.0,
                    "95.0" : 9.0,
                    "99.0" : 9.0,
                    "99.9" : 9.0,
                    "99.99" : 9.0,
                    "99.999" : 9.0,
                    "99.9999" : 9.0,
                    "100.0" : 9.0
                },
                "scoreUnit" : "ms",
                "rawData" : [
                    [
                        9.0,
                        7.0,
                        7.0,
                        7.0,
                        7.0
                    ]
                ]
            }
        }
    }
]


