[
    {
        "jmhVersion" : "1.37",
        "benchmark" : "me.ahoo.wow.benchmark.component.CommandPipelineComponentBenchmark.handleAggregateOnly",
        "mode" : "thrpt",
        "threads" : 16,
        "forks" : 5,
        "jvm" : "/Library/Java/JavaVirtualMachines/zulu-17.jdk/Contents/Home/bin/java",
        "jvmArgs" : [
            "-Xms2g",
            "-Xmx2g",
            "-XX:+UseG1GC"
        ],
        "jdkVersion" : "17.0.7",
        "vmName" : "OpenJDK 64-Bit Server VM",
        "vmVersion" : "17.0.7+7-LTS",
        "warmupIterations" : 3,
        "warmupTime" : "2 s",
        "warmupBatchSize" : 1,
        "measurementIterations" : 7,
        "measurementTime" : "2 s",
        "measurementBatchSize" : 1,
        "primaryMetric" : {
            "score" : 829740.7071554331,
            "scoreError" : 18092.12433739226,
            "scoreConfidence" : [
                811648.5828180409,
                847832.8314928254
            ],
            "scorePercentiles" : {
                "0.0" : 780237.2650579513,
                "50.0" : 824240.3088116322,
                "90.0" : 875253.0705948859,
                "95.0" : 876294.4216297442,
                "99.0" : 876409.5080470751,
                "99.9" : 876409.5080470751,
                "99.99" : 876409.5080470751,
                "99.999" : 876409.5080470751,
                "99.9999" : 876409.5080470751,
                "100.0" : 876409.5080470751
            },
            "scoreUnit" : "ops/s",
            "rawData" : [
                [
                    819790.1603596124,
                    822586.4326716358,
                    825996.1845398932,
                    799568.9281108213,
                    780237.2650579513,
                    781581.5451397134,
                    785945.1783518521
                ],
                [
                    824240.3088116322,
                    823134.7967529648,
                    825645.946620517,
                    807100.8349521079,
                    828682.3396025477,
                    823392.4937149324,
                    834878.5261274423
                ],
                [
                    866981.9921060258,
                    875008.0014568776,
                    876409.5080470751,
                    875620.6743018983,
                    876265.6500254115,
                    857873.63979305,
                    781773.046254947
                ],
                [
                    807843.625698739,
                    824269.6720836108,
                    822976.6646559675,
                    793310.2112212426,
                    805625.3869979219,
                    806059.7287052433,
                    816486.9525852953
                ],
                [
                    864487.4915785339,
                    856384.8303164527,
                    819625.4682792327,
                    852556.4064179043,
                    866535.4279901345,
                    864909.4272655895,
                    847140.0038453824
                ]
            ]
        },
        "secondaryMetrics" : {
            "gc.alloc.rate" : {
                "score" : 5563.589478069507,
                "scoreError" : 124.15516216769123,
                "scoreConfidence" : [
                    5439.434315901816,
                    5687.744640237198
                ],
                "scorePercentiles" : {
                    "0.0" : 5224.324495677481,
                    "50.0" : 5526.800858747227,
                    "90.0" : 5874.580498931362,
                    "95.0" : 5881.515434761451,
                    "99.0" : 5882.590284379376,
                    "99.9" : 5882.590284379376,
                    "99.99" : 5882.590284379376,
                    "99.999" : 5882.590284379376,
                    "99.9999" : 5882.590284379376,
                    "100.0" : 5882.590284379376
                },
                "scoreUnit" : "MB/sec",
                "rawData" : [
                    [
                        5489.9195386560705,
                        5508.0164348336975,
                        5531.133476192089,
                        5354.406065491242,
                        5224.324495677481,
                        5233.966218896786,
                        5254.510426976394
                    ],
                    [
                        5532.031849659567,
                        5524.779587505472,
                        5542.002296479165,
                        5417.388416888279,
                        5562.100302198993,
                        5526.800858747227,
                        5600.815190351436
                    ],
                    [
                        5819.022690576795,
                        5872.952199688575,
                        5882.590284379376,
                        5877.022947795542,
                        5881.246722356969,
                        5757.494610990205,
                        5243.832668772355
                    ],
                    [
                        5409.966026774192,
                        5519.61446975461,
                        5511.309236149482,
                        5312.465424332961,
                        5395.030618115054,
                        5397.946916792851,
                        5464.777419219373
                    ],
                    [
                        5802.426593147849,
                        5748.050301712631,
                        5501.224472147932,
                        5722.408634830011,
                        5816.015271453405,
                        5805.099699720129,
                        5682.939365168535
                    ]
                ]
            },
            "gc.alloc.rate.norm" : {
                "score" : 7033.626688871761,
                "scoreError" : 4.839972501822013,
                "scoreConfidence" : [
                    7028.786716369939,
                    7038.466661373583
                ],
                "scorePercentiles" : {
                    "0.0" : 7024.005299199159,
                    "50.0" : 7040.005120677295,
                    "90.0" : 7040.061626313812,
                    "95.0" : 7040.152234389621,
                    "99.0" : 7040.156200285247,
                    "99.9" : 7040.156200285247,
                    "99.99" : 7040.156200285247,
                    "99.999" : 7040.156200285247,
                    "99.9999" : 7040.156200285247,
                    "100.0" : 7040.156200285247
                },
                "scoreUnit" : "B/op",
                "rawData" : [
                    [
                        7024.005299199159,
                        7024.0053991515615,
                        7024.005452351387,
                        7024.005613352294,
                        7024.005760446089,
                        7024.005721832671,
                        7024.171309300131
                    ],
                    [
                        7040.005330270405,
                        7040.005355258391,
                        7040.0056217453175,
                        7040.005481825388,
                        7040.00530040439,
                        7040.005279641624,
                        7040.151242915715
                    ],
                    [
                        7040.00504795732,
                        7040.00501980738,
                        7040.005120677295,
                        7040.005144129018,
                        7040.005017496868,
                        7040.00513252317,
                        7040.156200285247
                    ],
                    [
                        7024.00536778279,
                        7024.005309372591,
                        7024.005337192011,
                        7024.005610508235,
                        7024.005451878261,
                        7024.005508745381,
                        7024.1494374099475
                    ],
                    [
                        7040.005163007995,
                        7040.00526103641,
                        7040.005533715145,
                        7040.005226935329,
                        7040.005180213885,
                        7040.005238976272,
                        7040.145633166554
                    ]
                ]
            },
            "gc.count" : {
                "score" : 319.0,
                "scoreError" : "NaN",
                "scoreConfidence" : [
                    319.0,
                    319.0
                ],
                "scorePercentiles" : {
                    "0.0" : 8.0,
                    "50.0" : 9.0,
                    "90.0" : 10.0,
                    "95.0" : 10.0,
                    "99.0" : 10.0,
                    "99.9" : 10.0,
                    "99.99" : 10.0,
                    "99.999" : 10.0,
                    "99.9999" : 10.0,
                    "100.0" : 10.0
                },
                "scoreUnit" : "counts",
                "rawData" : [
                    [
                        9.0,
                        9.0,
                        9.0,
                        9.0,
                        8.0,
                        9.0,
                        8.0
                    ],
                    [
                        10.0,
                        9.0,
                        9.0,
                        9.0,
                        9.0,
                        9.0,
                        9.0
                    ],
                    [
                        10.0,
                        9.0,
                        10.0,
                        10.0,
                        9.0,
                        10.0,
                        8.0
                    ],
                    [
                        9.0,
                        9.0,
                        9.0,
                        9.0,
                        8.0,
                        9.0,
                        9.0
                    ],
                    [
                        10.0,
                        9.0,
                        9.0,
                        10.0,
                        9.0,
                        10.0,
                        9.0
                    ]
                ]
            },
            "gc.time" : {
                "score" : 298.0,
                "scoreError" : "NaN",
                "scoreConfidence" : [
                    298.0,
                    298.0
                ],
                "scorePercentiles" : {
                    "0.0" : 7.0,
                    "50.0" : 8.0,
                    "90.0" : 9.0,
                    "95.0" : 10.199999999999996,
                    "99.0" : 11.0,
                    "99.9" : 11.0,
                    "99.99" : 11.0,
                    "99.999" : 11.0,
                    "99.9999" : 11.0,
                    "100.0" : 11.0
                },
                "scoreUnit" : "ms",
                "rawData" : [
                    [
                        8.0,
                        8.0,
                        8.0,
                        9.0,
                        8.0,
                        10.0,
                        8.0
                    ],
                    [
                        9.0,
                        8.0,
                        8.0,
                        9.0,
                        8.0,
                        8.0,
                        8.0
                    ],
                    [
                        8.0,
                        9.0,
                        9.0,
                        9.0,
                        7.0,
                        11.0,
                        9.0
                    ],
                    [
                        9.0,
                        8.0,
                        8.0,
                        9.0,
                        8.0,
                        8.0,
                        9.0
                    ],
                    [
                        9.0,
                        8.0,
                        9.0,
                        9.0,
                        8.0,
                        9.0,
                        8.0
                    ]
                ]
            }
        }
    }
]


